pymongoexpr/__init__.py
pymongoexpr/_version.py
pymongoexpr-0.1.1.dist-info/METADATA
pymongoexpr-0.1.1.dist-info/WHEEL
pymongoexpr-0.1.1.dist-info/RECORD
