Metadata-Version: 2.1
Name: pymongoexpr
Version: 0.1.1
Summary: Simple MongoDB filter expression parsing library
License: MIT
Author: Amir Nagri
Author-email: amir.nagri@proton.me
Requires-Python: >=3.8.1,<3.12
Classifier: License :: OSI Approved :: MIT License
Classifier: Programming Language :: Python :: 3
Classifier: Programming Language :: Python :: 3.9
Classifier: Programming Language :: Python :: 3.10
Classifier: Programming Language :: Python :: 3.11
